supersense/__init__.py
supersense/arms/__init__.py
supersense/arms/agilex_mujoco.py
supersense/arms/traj_joints.py
supersense/arms/traj_joints_pin.py
supersense/arms/traj_joints_pink.py
supersense/arms/traj_joints_pink_fr.py
supersense/arms/traj_joints_pink_piper.py
supersense/arms/tests/traj_joints_pink.py
supersense/arms/tests/traj_joints_pink2.py
supersense/arms/tests/traj_joints_pink3.py
supersense/cams/__init__.py
supersense/cams/base.py
supersense/cams/cam.py
supersense/depth/__init__.py
supersense/depth/da3.py
supersense/depth/Depth-Anything-3/src/depth_anything_3/api.py
supersense/depth/Depth-Anything-3/src/depth_anything_3/cfg.py
supersense/depth/Depth-Anything-3/src/depth_anything_3/cli.py
supersense/depth/Depth-Anything-3/src/depth_anything_3/registry.py
supersense/depth/Depth-Anything-3/src/depth_anything_3/specs.py
supersense/depth/Depth-Anything-3/src/depth_anything_3/app/css_and_html.py
supersense/depth/Depth-Anything-3/src/depth_anything_3/app/gradio_app.py
supersense/depth/Depth-Anything-3/src/depth_anything_3/app/modules/__init__.py
supersense/depth/Depth-Anything-3/src/depth_anything_3/app/modules/event_handlers.py
supersense/depth/Depth-Anything-3/src/depth_anything_3/app/modules/file_handlers.py
supersense/depth/Depth-Anything-3/src/depth_anything_3/app/modules/model_inference.py
supersense/depth/Depth-Anything-3/src/depth_anything_3/app/modules/ui_components.py
supersense/depth/Depth-Anything-3/src/depth_anything_3/app/modules/utils.py
supersense/depth/Depth-Anything-3/src/depth_anything_3/app/modules/visualization.py
supersense/depth/Depth-Anything-3/src/depth_anything_3/configs/da3-base.yaml
supersense/depth/Depth-Anything-3/src/depth_anything_3/configs/da3-giant.yaml
supersense/depth/Depth-Anything-3/src/depth_anything_3/configs/da3-large.yaml
supersense/depth/Depth-Anything-3/src/depth_anything_3/configs/da3-small.yaml
supersense/depth/Depth-Anything-3/src/depth_anything_3/configs/da3metric-large.yaml
supersense-0.1.1.dist-info/METADATA
supersense-0.1.1.dist-info/WHEEL
supersense-0.1.1.dist-info/entry_points.txt
supersense-0.1.1.dist-info/top_level.txt
supersense-0.1.1.dist-info/RECORD
