Metadata-Version: 2.4
Name: supersense
Version: 0.1.1
Summary: Supersense project
Author: Jin
License: MIT
Requires-Python: >=3.9
Requires-Dist: torch
Requires-Dist: opencv-python
Requires-Dist: pyyaml
Provides-Extra: dev
Requires-Dist: pytest; extra == "dev"
Requires-Dist: black; extra == "dev"
Requires-Dist: isort; extra == "dev"
Requires-Dist: mypy; extra == "dev"
